Workbook
Name August: #REF!
Name July: #REF!
Name May: #REF!
Name November: #REF!
Name October: #REF!
Name September: #REF!

Sheet Stmt of Changes in Ass
A1: Republic of the Philippines
A2: Province of Leyte
A3: Municipality of Jaro
A5: Statement of Changes in Net Assets/Equity
A7: For the Year Ended December 31, 2020
H9: Accumulated
H10: Surpluses/(Deficits)
H12: 2019 | J12: 2021
A14: Beginning Balance as of January 01,2020 | J14: 3.2815843e+08 | K14: Gov. Equity
A15: Add (Deduct)
B16: Change in Accounting Policy
B17: Prior Period Errors | J17: -13239701 | K17: Prior Period
A18: Restated Balance | J18: =J14+J17 -> 3.1491873e+08
A19: Add (Deduct) Changes in Net Assets/Equity dering the year
A20: Adjustment of net revenue recognized directly in net assets/equity | J20: 16977113
A21: Surplus (Deficit) for the period | J21: 51461424 | K21: Income
A22: Total recognized revenue and expenses for the period | J22: =SUM(J20:J21) -> 68438537
A24: Balance at March 31,2022. | J24: =J18+J22 -> 3.8335727e+08 | K24: checking balances
A28: Prepared by: | F28: Certified Correct:
A31: JJUVELYN A. CABARRUBIAS | F31: JUDY G. PARADO, CPA
A32: Job Order Employee | F32: Municipal Accountant

Sheet Schedule FP
A1: Republic of the Philippines
A2: Province of Leyte
A3: Municipality of Jaro
A5: SCHEDULE FOR INCOME AND EXPENSES
A6: For the Quarter Ended March 2022
A7: GENERAL FUND
A9: Account Code | E9: ACCOUNT TITLE | F9: AMOUNT
A11: 4 | B11: I N C O M E
A12: 4 | B12: 01 | C12: TAX REVENUE
A13: 4 | B13: 01 | C13: 01 | D13: Tax Revenue - Individual and Corporation
A14: 4 | B14: 01 | C14: 01 | D14: 020 | E14: Professional Tax | F14: =#REF! -> #REF!
A15: 4 | B15: 01 | C15: 01 | D15: 050 | E15: Community Tax | F15: =#REF! -> #REF!
A16: 4 | B16: 01 | C16: 02 | D16: Tax Revenue - Property
A17: 4 | B17: 01 | C17: 02 | D17: 040 | E17: Real Property Tax- Basic | F17: =#REF! -> #REF!
A18: 4 | B18: 01 | C18: 02 | D18: 041 | E18: Discount on Real Property Tax- Basic | F18: =SUM(-#REF!) -> #REF!
A19: 4 | B19: 01 | C19: 02 | D19: 050 | E19: Special Education Tax | F19: 0
A20: 4 | B20: 01 | C20: 02 | D20: 051 | E20: Discount on Special Education Tax | F20: 0
A21: 4 | B21: 01 | C21: 02 | D21: 060 | E21: Special Levy on Idle Lands | F21: 0
A22: 4 | B22: 01 | C22: 02 | D22: 070 | E22: Special Levy on Lands Benefited by Public Works Projects | F22: 0
A23: 4 | B23: 01 | C23: 02 | D23: 080 | E23: Real Property Transfer Tax | F23: =#REF! -> #REF!
A24: 4 | B24: 01 | C24: 03 | D24: Tax Revenue - Goods and Services
A25: 4 | B25: 01 | C25: 03 | D25: 030 | E25: Business Tax | F25: =#REF! -> #REF!
A26: 4 | B26: 01 | C26: 03 | D26: 040 | E26: Tax on Sand, Gravel and Other Quarry Products | F26: =#REF! -> #REF!
A27: 4 | B27: 01 | C27: 03 | D27: 050 | E27: Tax on Delivery Trucks and Vans | F27: =#REF! -> #REF!
A28: 4 | B28: 01 | C28: 03 | D28: 060 | E28: Amusement Tax | F28: =#REF! -> #REF!
A29: 4 | B29: 01 | C29: 03 | D29: 070 | E29: Franchise Tax | F29: =#REF! -> #REF!
A30: 4 | B30: 01 | C30: 03 | D30: 080 | E30: Printing and Publication Tax | F30: 0
A31: 4 | B31: 01 | C31: 04 | D31: Tax Revenue - Others
A32: 4 | B32: 01 | C32: 04 | D32: 990 | E32: Other Taxes | F32: 0
A33: 4 | B33: 01 | C33: 05 | D33: Tax Revenue - Fines and Penalties
A34: 4 | B34: 01 | C34: 05 | D34: 010 | E34: Tax Revenue - Fines and Penalties - Taxes on Individual and Corporation | F34: 0
A35: 4 | B35: 01 | C35: 05 | D35: 020 | E35: Tax Revenue - Fines and Penalties - Property Taxes
A36: 4 | B36: 01 | C36: 05 | D36: 030 | E36: Tax Revenue - Fines and Penalties - Taxes on Goods and Services
A37: 4 | B37: 01 | C37: 05 | D37: 040 | E37: Tax Revenue - Fines and Penalties - Other Taxes
A38: TOTAL
A39: 4 | B39: 01 | C39: 06 | D39: Share from National Taxes
A40: 4 | B40: 01 | C40: 06 | D40: 010 | E40: Share from Internal Revenue Collections (IRA) | H40: =SUM(#REF!) -> #REF!
A41: 4 | B41: 01 | C41: 06 | D41: 020 | E41: Share from Expanded Value Added Tax | H41: =SUM(F38,F45,F90,F110)-F18 -> #REF! | I41: =H40-H41 -> #REF!
A42: 4 | B42: 01 | C42: 06 | D42: 030 | E42: Share from National Wealth
A43: 4 | B43: 01 | C43: 06 | D43: 040 | E43: Share from Tobacco Excise Tax (RA 7171 and 8240)
A44: 4 | B44: 01 | C44: 06 | D44: 050 | E44: Share from Economic Zones
A45: TOTAL
A46: 4 | B46: 02 | C46: SERVICE AND BUSINESS INCOME
A47: 4 | B47: 02 | C47: 01 | D47: Service Income
A48: 4 | B48: 02 | C48: 01 | D48: 010 | E48: Permit Fees
A49: 4 | B49: 02 | C49: 01 | D49: 020 | E49: Registration Fees
A50: 4 | B50: 02 | C50: 01 | D50: 030 | E50: Registration Plates, Tags and Stickers Fees
A51: 4 | B51: 02 | C51: 01 | D51: 040 | E51: Clearance and Certification Fees
A52: 4 | B52: 02 | C52: 01 | D52: 070 | E52: Supervision and Regulation Enforcement Fees
A53: 4 | B53: 02 | C53: 01 | D53: 100 | E53: Inspection Fees
A54: 4 | B54: 02 | C54: 01 | D54: 110 | E54: Verification and Authentication Fees
A55: 4 | B55: 02 | C55: 01 | D55: 130 | E55: Processing Fees
A56: 4 | B56: 02 | C56: 01 | D56: 140 | E56: Occupation Fees
A57: 4 | B57: 02 | C57: 01 | D57: 150 | E57: Fishery Rental Fees
A58: 4 | B58: 02 | C58: 01 | D58: 160 | E58: Fees for Sealing and Licensing of Weights and Measures
A59: 4 | B59: 02 | C59: 01 | D59: 980 | E59: Fines and Penalties - Service Income
A60: 4 | B60: 02 | C60: 01 | D60: 990 | E60: Other Service Income
A61: 4 | B61: 02 | C61: 02 | D61: Business Income
A62: 4 | B62: 02 | C62: 02 | D62: 010 | E62: School Fees
A63: 4 | B63: 02 | C63: 02 | D63: 020 | E63: Affiliation Fees
A64: 4 | B64: 02 | C64: 02 | D64: 040 | E64: Seminar/Training Fees
A65: 4 | B65: 02 | C65: 02 | D65: 050 | E65: Rent Income
A66: 4 | B66: 02 | C66: 02 | D66: 060 | E66: Communication Network Fees
A67: 4 | B67: 02 | C67: 02 | D67: 070 | E67: Transportation System Fees
A68: 4 | B68: 02 | C68: 02 | D68: 080 | E68: Road Network Fees
A69: 4 | B69: 02 | C69: 02 | D69: 090 | E69: Waterworks System Fees
A70: 4 | B70: 02 | C70: 02 | D70: 100 | E70: Power Supply System Fees
A71: 4 | B71: 02 | C71: 02 | D71: 110 | E71: Seaport System Fees
A72: 4 | B72: 02 | C72: 02 | D72: 120 | E72: Parking Fees
A73: 4 | B73: 02 | C73: 02 | D73: 130 | E73: Receipts from Operation of Hostels/Dormitories and Other Like Facilities
... A89: 4 | B89: 02 | C89: 02 | D89: 990 | E89: Other Business Income
A90: TOTAL
A91: 4 | B91: 03 | C91: TRANSFERS, ASSISTANCE AND SUBSIDY
A92: 4 | B92: 03 | C92: 01 | D92: Assistance and Subsidy
A93: 4 | B93: 03 | C93: 01 | D93: 010 | E93: Subsidy from National Government
A94: 4 | B94: 03 | C94: 01 | D94: 020 | E94: Subsidy from Local Government Units
A95: 4 | B95: 03 | C95: 01 | D95: 030 | E95: Subsidy from Government-Owned and/or Controlled Corporations
A96: 4 | B96: 03 | C96: 01 | D96: 040 | E96: Subsidy from Other Funds
A97: 4 | B97: 03 | C97: 01 | D97: 050 | E97: Subsidy from General Fund Proper/Other Special Accounts
A98: 4 | B98: 03 | C98: 01 | D98: 060 | E98: Subsidy from Other Local Economic Enterprise
A99: 4 | B99: 03 | C99: 02 | D99: Transfers
A100: 4 | B100: 03 | C100: 02 | D100: 010 | E100: Transfers from General Fund as Project Equity Share
A101: 4 | B101: 03 | C101: 02 | D101: 020 | E101: Transfers from General Fund of Unspent DRRMF
A102: 4 | B102: 04 | C102: SHARES, GRANTS AND DONATIONS
A103: 4 | B103: 04 | C103: 01 | D103: Share
A104: 4 | B104: 04 | C104: 01 | D104: 010 | E104: Share from PAGCOR
A105: 4 | B105: 04 | C105: 01 | D105: 020 | E105: Share from PCSO
A106: 4 | B106: 04 | C106: 02 | D106: Grants and Donations
A107: 4 | B107: 04 | C107: 02 | D107: 010 | E107: Grants and Donations in Cash
A108: 4 | B108: 04 | C108: 02 | D108: 020 | E108: Grants and Donations in Kind
A109: 4 | B109: 04 | C109: 02 | D109: 030 | E109: Grants from Concessionary loans
A110: TOTAL
A111: 4 | B111: 05 | C111: GAINS
A112: 4 | B112: 05 | C112: 01 | D112: Gains
A113: 4 | B113: 05 | C113: 01 | D113: 010 | E113: Gain from Changes in Fair Value of Financial Instruments
A114: 4 | B114: 05 | C114: 01 | D114: 020 | E114: Gain on Foreign Exchange (FOREX)
A115: 4 | B115: 05 | C115: 01 | D115: 030 | E115: Gain on Sale of Investments
A116: 4 | B116: 05 | C116: 01 | D116: 040 | E116: Gain on Sale of Investment Property
A117: 4 | B117: 05 | C117: 01 | D117: 050 | E117: Gain on Sale of Property, Plant and Equipment
A118: 4 | B118: 05 | C118: 01 | D118: 060 | E118: Gain on Initial Recognition of Biological Assets
...

Sheet Stmt. of Fin'l. Performance
A1: Republic of the Philippines
A2: Province of Leyte
A3: MUNICIPALITY OF JARO
A5: STATEMENT OF FINANCIAL PERFORMANCE
A6: GENERAL FUND
A7: For the year ended December 31, 2020
A9: PARTICULARS | D9: 2019 | F9: 2021
A10: REVENUE
B11: Tax Revenue | D11: ='Schedule FP'!F38 -> 0 | F11: 4812161.3
B12: Share from Internal Revenue Collections | D12: =SUM('Schedule FP'!F45) -> 0 | F12: 166003264
B13: Other Share from National Taxes
B14: Service and Business Income | D14: =SUM('Schedule FP'!F90) -> 0 | F14: 10759217
B15: Shares, Grants and Donations | D15: =SUM('Schedule FP'!F110) -> 0 | F15: 415709.59
B16: Gains | D16: ='Schedule FP'!F132 -> 0 | F16: ='[1]Schedule FP'!H132 -> #REF!
B17: Other Income | D17: ='Schedule FP'!F132 -> 0 | F17: ='[1]Schedule FP'!H132 -> #REF!
A18: TOTAL REVENUE | D18: =SUM(D11:D17) -> 0 | F18: =SUM(F11:F17) -> #REF!
A19: Less: Current Operating Expenses
B20: Personnel Services | D20: ='Schedule FP'!F166 -> 0 | F20: 88363078
B21: Maintenance and Other Operating Expenses | D21: ='Schedule FP'!F257 -> 0 | F21: 38129411
B22: Financial Expenses | D22: =SUM('Schedule FP'!F266) -> 0 | F22: 21234.82
B23: Non-Cash Expenses | D23: ='Schedule FP'!F312 -> 0 | F23: 2972161.8
A24: CURRENT OPERATING EXPENSES | D24: =SUM(D20:D23) -> 0 | F24: =SUM(F20:F23) -> 1.2948589e+08
A25: Surplus (Deficit) from Current Operation | D25: =D18-D24 -> 0 | F25: =F18-F24 -> #REF!
B26: Add (Deduct):
C27: Transfers, Assistance and Subsidy from | D27: 0 | F27: 0
C28: Transfers, Assistance and Subsidy to LGUs | D28: =-'Schedule FP'!F235 -> 0 | F28: -1043041.9
A29: SURPLUS (DEFICIT) FOR THE PERIOD | D29: =D25+D28 -> 0 | F29: =F25+F28 -> #REF!
A31: Prepared by: | C31: Certified Correct:
B33: JUVELYN A. CABARRUBIAS | D33: JUDY G. PARADO, CPA
B34: Job Order Employee | D34: Municipal Accountant

Sheet Income Statement
A1: Republic of the Philippines
A2: Province of Leyte
A3: Municipality of Jaro
A5: STATEMENT OF INCOME AND EXPENSES
G6: General Fund
A7: For the Year Ended December 31, 2015
A8: (With Comparative Figures for CY 2014)
H11: 2015 | J11: 2014
A13: TAX REVENUE
B14: Local Taxes
C15: Amusement Tax | H15: =#REF! -> #REF! | J15: 3762.5
C16: Business Tax | H16: =#REF! -> #REF! | J16: 989643.8
C17: Community Tax | H17: =#REF! -> #REF! | J17: 615670.15
C18: Franchise Tax | H18: ='Schedule FP'!D17 -> 040 | J18: 1530
C19: Occupation Tax | H19: =#REF! -> #REF! | J19: 92820
C20: Printing and Publication Tax
C21: Property Transfer Tax
C22: Real Property Tax | H22: =#REF! -> #REF! | J22: 322494.86
D23: Less: Discount on Real Property Tax | H23: =-#REF! -> #REF! | J23: -42238.94
C24: Real Property Tax on Idle Lands
C25: Special Assessment Tax
C26: Special Education Tax
D27: Less: Discount on Special Education Tax
C28: Tax on Delivery Trucks and Vans | H28: =#REF! -> #REF! | J28: 30150
C29: Tax on Sand, Gravel and other Quarry Products | H29: =#REF! -> #REF! | J29: 70000
C30: Other Local Taxes | H30: =#REF! -> #REF! | J30: 8130
C31: Fines and Penalties-Local Taxes | H31: =#REF! -> #REF! | J31: 199482.86
C32: Total Local Taxes | H32: =SUM(H15:H31) -> #REF! | J32: =SUM(J15:J31) -> 2291445.2
A33: GENERAL INCOME ACCOUNTS
B34: Internal Revenue Allotment | H34: =#REF! -> #REF! | J34: 81867039
B35: Permits and Licenses
C36: Fees on Weights and Measures | H36: =#REF! -> #REF! | J36: 8870
C37: Fishery Rental Fees
C38: Franchising and Licensing Fees
C39: Motor Vehicles Users Charge
C40: Permit Fees | H40: =#REF! -> #REF! | J40: 463848.61
C41: Registration Fees | H41: =#REF! -> #REF! | J41: 68460
C42: Other Permits and Licenses | H42: =#REF! -> #REF! | J42: 132884.5
C43: Fines and Penalties - Permits and Licenses
C44: Total Permits and Licenses | H44: =SUM(H36:H43) -> #REF! | J44: =SUM(J36:J43) -> 674063.11
B45: Service Income
C46: Affiliation Fees
C47: Athletic and Cultural Fees
C48: Clearance and Certification Fees | H48: =#REF! -> #REF! | J48: 771501
C49: Comprehensive Examination Fees
C50: Diploma and Graduation Fees
C51: Garbage Fees | H51: =#REF! -> #REF! | J51: 112060
C52: Inspection Fees | H52: =#REF! -> #REF! | J52: 228189
C53: Library Fees
C54: Medical, Dental and Laboratory Fees
C55: Processing Fees
C56: Seminar Fees
C57: Toll and Terminal Fees
C58: Transcript of Record Fees
C59: Other Services Income | H59: =#REF! -> #REF! | J59: 293541
C60: Fines and Penalties - Service Income
C61: Total Service Income | H61: =SUM(H46:H60) -> #REF! | J61: =SUM(J46:J60) -> 1405291
B62: Business Income
C63: Hospital Fees
C64: Income from Canteen Operations
C65: Income from Cemetery Operations | H65: =#REF! -> #REF! | J65: 158370
C66: Income from Communication Facilities
C67: Income from Dormitory Operations
C68: Landing and Parking Fees
C69: Income from Markets | H69: =#REF! -> #REF! | J69: 732820
C70: Income from Slaughterhouse | H70: =#REF! -> #REF! | J70: 288740
C71: Income from Transportation System
C72: Income from Waterworks System
C73: Printing and Publication Income
C74: Rent Income | H74: =#REF! -> #REF! | J74: 25380
C75: Sales Revenue
D76: Cost of Goods Sold
C77: Net Sales Revenue
C78: Tuition Fees
C79: Other Business Income | H79: ='Schedule FP'!D48 -> 010 | J79: 32630
C80: Fines and Penalties - Business Income
C81: Total Business Income | H81: =SUM(H63:H80) -> #REF! | J81: =SUM(J63:J80) -> 1237940
B82: Other Income
C83: Dividend Income
C84: Income from Grants and Donations
C85: Insurance Income
C86: Interest Income | H86: =#REF! -> #REF! | J86: 58352.48
C87: Sale of Confiscated/Abandoned/Seized Goods and Properties
C88: Share from Economic Zones
C89: Share from Expanded Value Added Tax
C90: Share from National Wealth
C91: Share from PAGCOR/PCSO | H91: =#REF! -> #REF! | J91: 142167.82
C92: Share from Tobaco Excise Tax
C93: Miscellaneous Income
C94: Other Fines and Penalties
C95: Total Other Income | H95: =SUM(H83:H94) -> #REF! | J95: =SUM(J83:J94) -> 200520.3
B96: TOTAL OPERATING INCOME | H96: =H32+H34+H44+H61+H81+H95 -> #REF! | J96: =J32+J34+J44+J61+J81+J95 -> 87676299
A97: EXPENSES
B98: PERSONAL SERVICES
C99: Salaries and Wages
D100: Salaries and Wages - Regular | H100: =#REF! -> #REF! | J100: 33625969
D101: Salaries and Wages - Military/Uniformed
D102: Salaries and Wages - Part-time
D103: Salaries and Wages - Substitute
D104: Salaries and Wages - Casual | H104: =#REF! -> #REF! | J104: 4014741.3
...

Sheet Schedule Balance Sheet
A1: Republic of the Philippines
A2: Province of Leyte
A3: Municipality of Jaro
A5: SCHEDULE OF BALANCE SHEET
A6: As of December 31, 2015
A7: General Fund
B10: Account | D10: Amount
B11: Code
A12: Cash
A13: Cash in Vault | B13: 101 | E13: 3359712.5
A15: Petty Cash Fund (GF) | B15: 104-1 | E15: 23642.37
A16: Petty Cash Fund (AICS) | B16: 104-2 | E16: 20000
E17: =E15+E16 -> 43642.37
A19: Payroll Fund | B19: 106 | E19: =#REF! -> #REF!
A21: Cash in Bank-(LBP) IRA | B21: 111-1A | E21: 11642128
A22: Cash in Bank-(PNB)LARP Account | B22: 111-1B | E22: 14328.66
A23: Cash in Bank-(PNB)LGU Equity Account | B23: 111-1C | E23: 33326.04
A24: Cash in Bank-(PNB) 20% Development Fund Account | B24: 111-2 | E24: -15.49
A25: Cash in Bank-(PPSB) 5% Calamity Fund Account | B25: 111-3 | E25: 9081383
A26: Cash in Bank-(LBP) Performance Challenge Fund | B26: 111-7 | E26: 3799238.4
A27: Cash in Bank-(LBP) SALINTUBIG | B27: 111-8 | E27: 12452467
A28: Cash in Bank-(LBP) Flood Control | B28: 111-9 | E28: 8679983.7
A29: Cash in Bank-(LBP) Sports Complex | B29: 111-10 | E29: 1025000
A30: Cash in Bank-(LBP) RAY Project | B30: 111-11 | E30: 1272462.7
A31: Cash in Bank-(LBP) GPBP | B31: 111-12 | E31: 3010000
A32: Cash in Bank-(LBP) BRGY.FACILITIES (RAY) | B32: 111-13 | E32: 20153517
A33: Total | E33: =SUM(E21:E32) -> 71163818
A35: Total Cash | E35: =E13+E17+E33+E19 -> #REF!
A37: Receivables
A38: Real Property Tax Receivables | B38: 127 | E38: 24158078
A39: Due from NGAs | B39: 136 | E39: =#REF! -> #REF!
A40: Due from GOCCs | B40: 137 | E40: =#REF! -> #REF!
A41: Due from LGUs | B41: 138 | E41: =#REF! -> #REF!
A42: Due from Other Funds | B42: 144 | E42: 626192.34
A43: Receivables-Disallowances/Charges | B43: 146 | E43: 23333.02
A44: Advances to Officers and Employees | B44: 148 | E44: 4540207.9
A45: Other Receivables | B45: 149 | E45: =#REF! -> #REF!
A46: Total Receivables | E46: =SUM(E38:E45) -> #REF!
A48: Inventories
A49: Office Supplies Inventory | B49: 155 | E49: 17842.5
A50: Other Supplies Inventory | B50: 165 | E50: 145607.6
A51: Construction Materials Inventory | B51: 168 | E51: 180
A52: Livestock Inventory | B52: 169 | E52: =#REF! -> #REF!
A53: Total | E53: =SUM(E49:E52) -> #REF!
A55: Prepayments
A56: Prepaid Insurance | B56: 178 | E56: 12893.88
A57: Advances to Contractors | B57: 181 | E57: 323539.58
A58: Total | E58: =E56+E57 -> 336433.46
A60: Land and Land Improvements
A61: Land | B61: 201 | E61: 6961640
A62: Land Improvements | B62: 202 | E62: =#REF! -> #REF!
A63: Electrification, Power and Energy Structures | B63: 205 | D63: =#REF! -> #REF!
A64: Accumulated Depreciation-Electrification, Power and
A65: Energy Structures | B65: 305 | D65: 2526.57 | E65: =D63-D65 -> #REF!
A66: Total Land and Land Improvements | E66: =SUM(E61:E65) -> #REF!
A68: Buildings
A69: Office Buildings | B69: 211 | E69: =#REF! -> #REF!
A70: School Buildings | B70: 212 | E70: 3129562.1
A71: Market & SlaughterHouses | B71: 214 | E71: =#REF! -> #REF!
A72: Total Buildings | E72: =SUM(E69:E71) -> #REF!
A74: Office Equipment, Furniture & Fixtures
A75: Office Equipment | B75: 221 | E75: 412938
A76: Accumulated Depreciation-Office Equipment | B76: 321 | E76: 214397.84
A77: Net Amount | E77: =E75-E76 -> 198540.16
A79: Furniture and Fixtures | B79: 222 | E79: 1072313.1
A80: Accumulated Depreciation-Furniture & Fixtures | B80: 322 | E80: 549768.13
A81: Net Amount | E81: =E79-E80 -> 522544.95
A83: IT Equipment and Software | B83: 223 | E83: =#REF! -> #REF!
A84: Accumulated Depreciation-IT Equipment | B84: 323 | E84: =#REF! -> #REF!
A85: Net Amount | E85: =E83-E84 -> #REF!
A87: Library Books | B87: 224 | E87: =#REF! -> #REF!
A89: Net Total Office Equipment, Furniture and Fixtures | E89: =E77+E81+E85+E87 -> #REF!
A91: Machineries and Equipment
A92: Machinery | B92: 226 | E92: =#REF! -> #REF!
A93: Agricultural, Fishery and Forestry Equipment | B93: 227 | E93: =#REF! -> #REF!
A94: Communication Equipment | B94: 229 | E94: =#REF! -> #REF!
A95: Sports Equipment | B95: 235 | E95: =#REF! -> #REF!
A96: Technical & Scientific Equipment | B96: 236 | E96: =#REF! -> #REF!
A97: Other Machinery & Equipment | B97: 240 | E97: =#REF! -> #REF!
A98: Total | E98: =SUM(E92:E97) -> #REF!
A99: Less: Accumulated Depreciation-Machineries | B99: 326 | C99: =#REF! -> #REF!
A100: Accumulated Depreciation-Agricultural Eqpt. | B100: 327 | C100: =#REF! -> #REF!
A101: Accumulated Depreciation-Communication Eqpt. | B101: 329 | C101: =#REF! -> #REF!
A102: Accumulated Depreciation-Other Machineries | B102: 340 | C102: =#REF! -> #REF! | E102: =C99+C102+C100+C101 -> #REF!
A103: Net Amount | E103: =E98-E102 -> #REF!
A105: Construction & Heavy Equipment | B105: 230 | E105: =#REF! -> #REF!
A106: Accumulated Depreciation-Construction & Heavy Equip. | B106: 330 | E106: =#REF! -> #REF!
A107: Net Amount | E107: =E105-E106 -> #REF!
A109: Net Total Machineries and Equipment | E109: =E103+E107 -> #REF!
A111: Transportation and Equipment
A112: Motor Vehicles | B112: 241 | E112: =#REF! -> #REF!
A113: Less: Acculmulated Depreciiation-Motor Vehicles | B113: 341 | E113: =#REF! -> #REF!
A114: Net Amount | E114: =E112-E113 -> #REF!
A116: Other Property, Plant and Equipment | B116: 250 | E116: =#REF! -> #REF!
A117: Less: Acculmulated Depreciiation-Other PPE | B117: 350 | E117: =#REF! -> #REF!
A118: Net Amount | E118: =E116-E117 -> #REF!
A120: Construction in Progress
A121: Construction in Progress-Agency Assets | B121: 264 | E121: =#REF! -> #REF!
A122: Construction in Progress-Artesian Wells, Reservoirs,
A123: Pumping Stations & Conduits | B123: 269 | E123: 8977469.2
...

Sheet Sched. fin'l. Position
A1: Republic of the Philippines
A2: Province of Leyte
A3: Municipality of Jaro
A5: SCHEDULE OF STATEMENT OF FINANCIAL POSITION
A6: As of MARCH 31,2022
A7: GENERAL FUND
A9: Account Code | E9: ACCOUNT TITLE | F9: AMOUNT
A11: 1 | B11: 01 | C11: CASH
A12: 1 | B12: 01 | C12: 01 | D12: Cash on Hand
A13: 1 | B13: 01 | C13: 01 | D13: 010 | E13: Cash Local Treasury
A14: 1 | B14: 01 | C14: 01 | D14: 020 | E14: Petty Cash
A15: 1 | B15: 01 | C15: 02 | D15: Cash in Bank - Local Currency
A16: 1 | B16: 01 | C16: 02 | D16: 010 | E16: Cash in Bank - Local Currency, Current Account | I16: =F13+F14+F16 -> 0
A17: 1 | B17: 01 | C17: 02 | D17: 020 | E17: Cash in Bank - Local Currency, Savings Account
A18: 1 | B18: 01 | C18: 03 | D18: Cash in Bank - Foreign Currency
A19: 1 | B19: 01 | C19: 03 | D19: 010 | E19: Cash in Bank - Foreign Currency, Current Account
A20: 1 | B20: 01 | C20: 03 | D20: 020 | E20: Cash in Bank - Foreign Currency, Savings Account
A21: TOTAL
A22: 1 | B22: 02 | C22: INVESTMENTS
A23: 1 | B23: 02 | C23: 01 | D23: Investments in Time Deposits
A24: 1 | B24: 02 | C24: 01 | D24: 010 | E24: Cash in Bank -Local Currency, Time Deposits
A25: 1 | B25: 02 | C25: 01 | D25: 020 | E25: Cash in Bank - Foreign Currency, Time Deposits
A26: 1 | B26: 02 | C26: 01 | D26: 030 | E26: Treasury Bills
A27: 1 | B27: 02 | C27: 02 | D27: Financial Assets at Fair Value Through Surplus or Deficit
A28: 1 | B28: 02 | C28: 02 | D28: 010 | E28: Financial Assets Held for Trading
A29: 1 | B29: 02 | C29: 02 | D29: 020 | E29: Financial Assets Designated at Fair Value Through Surplus or Deficit
A30: 1 | B30: 02 | C30: 03 | D30: Financial Assets - Held to Maturity
A31: 1 | B31: 02 | C31: 03 | D31: 010 | E31: Investments in Treasury Bills - Local
A32: 1 | B32: 02 | C32: 03 | D32: 011 | E32: Allowance for Impairment - Investments in Treasury Bills - Local
A33: 1 | B33: 02 | C33: 03 | D33: 020 | E33: Investments in Bonds-Local
A34: 1 | B34: 02 | C34: 03 | D34: 021 | E34: Allowance for Impairment - Investments in Bonds - Local
A35: 1 | B35: 02 | C35: 04 | D35: Financial Assets - Available for Sale
A36: 1 | B36: 02 | C36: 04 | D36: 010 | E36: Investments in Stocks
A37: 1 | B37: 02 | C37: 04 | D37: 020 | E37: Investments in Bonds
A38: 1 | B38: 02 | C38: 05 | D38: Financial Assets - Others
A39: 1 | B39: 02 | C39: 05 | D39: 010 | E39: Deposits on Letters of Credit
A40: 1 | B40: 02 | C40: 05 | D40: 011 | E40: Allowance for Impairment - Deposits in Letters of Credit
A41: 1 | B41: 02 | C41: 05 | D41: 020 | E41: Guaranty Deposits
A42: 1 | B42: 02 | C42: 05 | D42: 021 | E42: Allowance for Impairment - Guaranty Deposits
A43: 1 | B43: 02 | C43: 05 | D43: 990 | E43: Other Investments
A44: 1 | B44: 02 | C44: 05 | D44: 991 | E44: Allowance for Impairment - Other Investments
A45: 1 | B45: 02 | C45: 06 | D45: Investments in Joint Venture
A46: 1 | B46: 02 | C46: 06 | D46: 010 | E46: Investments in Joint Venture
A47: 1 | B47: 02 | C47: 06 | D47: 011 | E47: Allowance for Impairment - Investments in Joint Venture
A48: 1 | B48: 02 | C48: 07 | D48: Sinking Fund
A49: 1 | B49: 02 | C49: 07 | D49: 010 | E49: Sinking Fund
A50: TOTAL
A51: 1 | B51: 03 | C51: RECEIVABLES
A52: 1 | B52: 03 | C52: 01 | D52: Loans and Receivable Accounts
A53: 1 | B53: 03 | C53: 01 | D53: 010 | E53: Accounts Receivable
A54: 1 | B54: 03 | C54: 01 | D54: 011 | E54: Allowance for Impairment - Accounts Receivable
A55: 1 | B55: 03 | C55: 01 | D55: 020 | E55: Real Property Tax Receivable
A56: 1 | B56: 03 | C56: 01 | D56: 021 | E56: Allowance for Impairment - RPT Receivable
A57: 1 | B57: 03 | C57: 01 | D57: 030 | E57: Special Education Tax Receivable
A58: 1 | B58: 03 | C58: 01 | D58: 031 | E58: Allowance for Impairment - SET Receivable
A59: 1 | B59: 03 | C59: 01 | D59: 040 | E59: Notes Receivable
A60: 1 | B60: 03 | C60: 01 | D60: 041 | E60: Allowance for Impairment - Notes Receivable
A61: 1 | B61: 03 | C61: 01 | D61: 050 | E61: Loans Receivable - Government-Owned and/or Controlled Corporations
A62: 1 | B62: 03 | C62: 01 | D62: 051 | E62: Allowance for Impairment - Loans Receivable - Government-Owned and/or Controlled Corporations
A63: 1 | B63: 03 | C63: 01 | D63: 060 | E63: Loans Receivable - Local Government Units
A64: 1 | B64: 03 | C64: 01 | D64: 061 | E64: Allowance for Impairment - Loans Receivable - Local Government Units
... A70: 1 | B70: 03 | C70: 01 | D70: 991 | E70: Allowance for Impairment - Loans Receivable - Others
A71: 1 | B71: 03 | C71: 02 | D71: Lease Receivables
A72: 1 | B72: 03 | C72: 02 | D72: 010 | E72: Operating Lease Receivable
A73: 1 | B73: 03 | C73: 02 | D73: 011 | E73: Allowance for Impairment - Operating Lease Receivable
A74: 1 | B74: 03 | C74: 02 | D74: 020 | E74: Finance Lease Receivable
A75: 1 | B75: 03 | C75: 02 | D75: 021 | E75: Allowance for Impairment - Finance Lease Receivable
A76: 1 | B76: 03 | C76: 03 | D76: Inter-Agency Receivables
A77: 1 | B77: 03 | C77: 03 | D77: 010 | E77: Due from National Government Agencies
A78: 1 | B78: 03 | C78: 03 | D78: 011 | E78: Allowance for Impairment - Due from National Government Agencies
A79: 1 | B79: 03 | C79: 03 | D79: 020 | E79: Due from Government-Owned and/or Controlled Corporations
A80: 1 | B80: 03 | C80: 03 | D80: 021 | E80: Allowance for Impairment - Due from GOCCs
A81: 1 | B81: 03 | C81: 03 | D81: 030 | E81: Due from Local Government Units
A82: 1 | B82: 03 | C82: 03 | D82: 031 | E82: Allowance for Impairment - Due from LGUs
A83: 1 | B83: 03 | C83: 03 | D83: 040 | E83: Due from Joint Venture
A84: 1 | B84: 03 | C84: 03 | D84: 041 | E84: Allowance for Impairment - Due from Joint Venture
A85: 1 | B85: 03 | C85: 04 | D85: Intra-Agency Receivables
A86: 1 | B86: 03 | C86: 04 | D86: 050 | E86: Due from Other Funds
A87: 1 | B87: 03 | C87: 04 | D87: 060 | E87: Due from Special Accounts
A88: 1 | B88: 03 | C88: 04 | D88: 070 | E88: Due from Local Economic Enterprise
A89: 1 | B89: 03 | C89: 05 | D89: Advances
A90: 1 | B90: 03 | C90: 05 | D90: 010 | E90: Advances for Operating Expenses
A91: 1 | B91: 03 | C91: 05 | D91: 020 | E91: Advances for Payroll
A92: 1 | B92: 03 | C92: 05 | D92: 030 | E92: Advances to Special Disbursing Officer
A93: 1 | B93: 03 | C93: 05 | D93: 040 | E93: Advances for Officers and Employees
A94: 1 | B94: 03 | C94: 06 | D94: Other Receivables
A95: 1 | B95: 03 | C95: 06 | D95: 010 | E95: Receivables - Disallowances/Charges
A96: 1 | B96: 03 | C96: 06 | D96: 011 | E96: Allowance for Impairment - Receivables- Disallowances/Charges
A97: 1 | B97: 03 | C97: 06 | D97: 020 | E97: Due from Officers and Employees
A98: 1 | B98: 03 | C98: 06 | D98: 021 | E98: Allowance for Impairment - Due from Officers and Employees
A99: 1 | B99: 03 | C99: 06 | D99: 030 | E99: Due from Non-Government Organizations/People's Organizations
A100: 1 | B100: 03 | C100: 06 | D100: 031 | E100: Allowance for Impairment - Due from Non-Government Organizations/People's Organizations
A101: 1 | B101: 03 | C101: 06 | D101: 990 | E101: Other Receivables
A102: 1 | B102: 03 | C102: 06 | D102: 991 | E102: Allowance for Impairment - Other Receivables
A103: TOTAL
A104: 1 | B104: 04 | C104: INVENTORIES
A105: 1 | B105: 04 | C105: 01 | D105: Inventory Held for Sale
A106: 1 | B106: 04 | C106: 01 | D106: 010 | E106: Merchandise Inventory
A107: 1 | B107: 04 | C107: 02 | D107: Inventory Held for Distribution
A108: 1 | B108: 04 | C108: 02 | D108: 010 | E108: Food Supplies for Distribution
...

Sheet Detailed Fin'L Position 
A1: MUNICIPALITY OF JARO
A2: Statement of Financial Position
A3: As of March 31,2022
A7: ASSETS
B8: CURRENT ASSETS
C9: CASH AND CASH EQUIVALENTS
D10: Cash on Hand
E11: Cash Local Treasury | O11: ='Sched. fin''l. Position'!F13 -> 0
E12: Petty Cash
D13: Cash in Banks - Local Currency
E14: Cash in Bank - Local Currency , Current Account
E15: Cash in Bank - Local Currency, Savings Account | O15: ='Sched. fin''l. Position'!F17 -> 0 | S15: ='[2]2019'!$E$13 -> 20343197
D16: Cash in Banks - Foreign Currency
E17: Cash in Bank - Foreign Currency , Current Account
E18: Cash in Bank - Foreign Currency, Savings Account
D19: Investments in Time Deposits (90 days)
E20: Cash in Bank -Local Currency, Time Deposits
E21: Cash in Bank - Foreign Currency, Time Deposits
E22: Treasury Bills
D23: Total Cash and Cash Equivalents
C24: INVESTMENTS
D25: Investments in Time Deposits (91 days to 1 year)
E26: Cash in Bank -Local Currency, Time Deposits
E27: Cash in Bank - Foreign Currency, Time Deposits
E28: Treasury Bills
D29: Financial Assets at Fair Value Through Surplus or Deficit
E30: Financial Assets Held for Trading
E31: Financial Assets Designated at Fair Value Through Surplus or Deficit
D32: Financial Assets - Held to Maturity
E33: Investments in Treasury Bills - Local
E34: Allowance for Impairment - Investments in Treasury Bills - Local
E35: Investments in Bonds-Local
E36: Allowance for Impairment - Investments in Bonds - Local
D37: Financial Assets - Available for Sale
E38: Investments in Stocks
E39: Investments in Bonds
D40: Financial Assets - Others
E41: Deposits on Letters of Credit
E42: Allowance for Impairment - Deposits in Letters of Credit
E43: Guaranty Deposits
E44: Allowance for Impairment - Guaranty Deposits
E45: Other Investments
E46: Allowance for Impairment - Other Investments
D47: Investments in Joint Venture
E48: Investments in Joint Venture
E49: Allowance for Impairment - Investments in Joint Venture
D50: Sinking Fund
E51: Sinking Fund
D52: Total Investments
C53: RECEIVABLES
D54: Loans and Receivable Accounts
E55: Accounts Receivable
E56: Allowance for Impairment - Accounts Receivable
E57: Real Property Tax Receivable | O57: ='Sched. fin''l. Position'!F55 -> 0
E58: Allowance for Impairment - RPT Receivable
E59: Special Education Tax Receivable
E60: Allowance for Impairment - SET Receivable
E61: Notes Receivable
E62: Allowance for Impairment - Notes Receivable
E63: Loans Receivable - Government-Owned and/or Controlled Corporations
E64: Allowance for Impairment - Loans Receivable - Government-Owned and/or Controlled Corporations
E65: Loans Receivable - Local Government Units
E66: Allowance for Impairment - Loans Receivable - Local Government Units
E67: Interests Receivable
E68: Allowance for Impairment - Interests Receivable
E69: Dividends Receivable
... E72: Allowance for Impairment - Loans Receivable - Others
D73: Lease Receivables
E74: Operating Lease Receivable
E75: Allowance for Impairment - Operating Lease Receivable
E76: Finance Lease Receivable
E77: Allowance for Impairment - Finance Lease Receivable
D78: Inter-Agency Receivables
E79: Due from National Government Agencies
E80: Allowance for Impairment - Due from National Government Agencies
E81: Due from Government-Owned and/or Controlled Corporations
E82: Allowance for Impairment - Due from GOCCs
E83: Due from Local Government Units
E84: Allowance for Impairment - Due from LGUs
E85: Due from Joint Venture
E86: Allowance for Impairment - Due from Joint Venture
D87: Intra-Agency Receivables
E88: Due from Other Funds | O88: ='Sched. fin''l. Position'!F86 -> 0
E89: Due from Special Accounts
E90: Due from Local Economic Enterprise
D91: Advances
E92: Advances for Operating Expenses | O92: ='Sched. fin''l. Position'!F90 -> 0
E93: Advances for Payroll | O93: ='Sched. fin''l. Position'!F91 -> 0
E94: Advances to Special Disbursing Officer
E95: Advances for Officers and Employees | O95: ='Sched. fin''l. Position'!F93 -> 0
D96: Other Receivables
E97: Receivables - Disallowances/Charges | O97: ='Sched. fin''l. Position'!F95 -> 0
E98: Allowance for Impairment - Receivables- Disallowances/Charges
E99: Due from Officers and Employees | O99: ='Sched. fin''l. Position'!F97 -> 0
E100: Allowance for Impairment - Due from Officers and Employees
E101: Due from Non-Government Organizations/People's Organizations
E102: Allowance for Impairment - Due from Non-Government Organizations/People's Organizations
E103: Other Receivables
E104: Allowance for Impairment - Other Receivables
E105: Total Receivables | S105: =SUM(O57:O105) -> 0 | U105: =S105-'Stmt. of Fin''l. Position'!D14 -> 0
...

Sheet Stmt. of Fin'l. Position
A1: Republic of the Philippines | H1: =H45 -> #REF!
A2: Province of Leyte
A3: MUNICIPALITY OF JARO
A5: STATEMENT OF FINANCIAL POSITION
A6: As of December 31, 2020
A7: GENERAL FUND
A9: PARTICULARS | D9: 2019 | F9: 2020
A10: ASSETS
B11: CURRENT ASSETS
C12: Cash and Cash Equivalents | D12: ='Sched. fin''l. Position'!F21 -> 0 | F12: 1.3458281e+08
C13: Investments
C14: Receivables | F14: 42773139
C15: Inventories | D15: ='Sched. fin''l. Position'!F157 -> 0 | F15: 6523268.8
C16: Prepayment and Deferred Charges | F16: 855449.75
A17: TOTAL CURRENT ASSETS | D17: =SUM(D12:D16) -> 0 | F17: =SUM(F12:F16) -> 1.8473467e+08
B18: NON-CURRENT ASSETS
C19: Investments | F19: =[4]DECEMBER!$J$14 -> 72000
C20: Receivables | F20: 168842.18
C21: Investment Property | F21: 2175110
C22: Property, Plant & Equipment | F22: 2.3472037e+08
C23: Biological Assets
C24: Intangible Assets | F24: 328599
A26: TOTAL NON-CURRENT ASSETS | F26: =SUM(F19:F24) -> 2.3746492e+08
A27: T O T A L A S S E T S | D27: =D17+D26 -> 0 | F27: =SUM(F17+F26) -> 4.2219959e+08
A28: LIABILITIES
B29: CURRENT LIABILITIES
C30: Financial Liabilities | D30: =SUM('Sched. fin''l. Position'!F360) -> 0 | F30: 67694.71
C31: Inter-Agency Payables | D31: ='Sched. fin''l. Position'!F387 -> 0 | F31: 14264606
C32: Intra-Agency Payables | D32: =SUM('Sched. fin''l. Position'!F393) -> 0 | F32: 5734628.4
C33: Trust Liablilities | D33: =SUM('Sched. fin''l. Position'!F401) -> 0 | F33: 1608601.6
C34: Deferred Credits/Unearned Income | F34: -
A35: TOTAL CURRENT LIABILITIES | D35: =SUM(D30:D34) -> 0 | F35: =SUM(F30:F34) -> 21675531
B36: NON-CURRENT LIABILITIES
C37: Financial Liablilities | D37: =SUM('Sched. fin''l. Position'!F374) -> 0 | F37: 464169.2
C38: Deferred Credits/Unearned Income | D38: =SUM('Sched. fin''l. Position'!F410) -> 0 | F38: 16156053
C39: Provisions | D39: ='Sched. fin''l. Position'!F415 -> 0
C40: Other Payables | D40: =SUM('Sched. fin''l. Position'!F418) -> 0 | F40: 546567.84
A41: TOTAL NON-CURRENT LIABILITIES | D41: =SUM(D37:D40) -> 0 | F41: =SUM(F37:F40) -> 17166790
A42: T O T A L L I A B I L I T I E S | D42: =SUM(D35,D41) -> 0 | F42: =SUM(F35+F41) -> 38842321
A43: NET ASSETS/EQUITY
B44: Government Equity | D44: =#REF! -> #REF! | F44: 3.8335727e+08
A45: TOTAL LIABILITIES AND NET ASSETS/EQUITY | D45: =SUM(D42+D44) -> #REF! | F45: =SUM(F44+F42) -> 4.2219959e+08 | H45: =D27-D45 -> #REF! | I45: Checking Balances
A48: Prepared by: | C48: Certified Correct:
B50: JUVELYN A. CABARRUBIAS | D50: JUDY G. PARADO, CPA
B51: Job Order Employee | D51: Municipal Accountant

Sheet CASH FLOW
A1: Republic of the Philippines
A2: Province of Leyte
A3: Municipality of Jaro
A5: STATEMENT OF CONDENSED CASH FLOWS
A6: GENERAL FUND
A7: As of March 31,2022
A8: P A R T I C U L A R S | F8: 2019
A9: CASH FLOW FROM OPERATING ACTIVITIES
A10: Cash Inflows
B11: Collection from Taxpayers
B12: Share from Internal Revenue Allotment
B13: Receipts from Business/Service Income
B14: Interest Income
B15: Dividend Income
B16: Other Receipts
B17: Total Cash Inflows | I17: =SUM(I12:I16) -> 0
A18: Cash Outflows
B19: Payment of Expenses
B20: Payments to Suppliers and Creditors | K20: 22617691
B21: Payments to Employees | K21: 69810565
B22: Interest Expense
B23: Other Expenses | K23: 99345644
B24: Total Cash Outflows
A25: Net Cash Flows from Operating Activities
A26: CASH FLOW FROM INVESTING ACTIVITIES
A27: Cash Inflows
B28: Proceeds from Sale of Investment Property
B29: Proceeds from Sale/Disposal of Property, Plant and Equipment
B30: Proceeds from Sale of Non-Current Investments
B31: Collection of Principal on Loans to Other Entities
B32: Total Cash Inflows
A33: Cash Outflows
B34: Purchase/Construction of Investment Property
B35: Purchase/Construction of Property, Plant and Equipment | K35: 6081097.3
B36: Investment
B37: Purchase of Bearer Biological Assets
B38: Purchase of Intangible Assets
B39: Grant of Loans
B40: Total Cash Outflows
A41: Net Cash Flows from Investing Activities
A42: CASH FLOWS FROM FINANCING ACTIVITIES
A43: Cash Inflows
B44: Proceeds from Issuance of Bonds
B45: Proceeds from Loans
B46: Total Cash Inflows
A47: Cash Outflows
B48: Payment of Long-Term Liabilities
B49: Retirement/Redemption of Debt Securities
B50: Payment of Loan Amortization
B51: Total Cash Outflows
A52: Net Cash Flows from Financing Activities
A53: Total Cash Provided by Operating, Investing and Financing Activities | I53: =F53-I17 -> 0
A54: Add: Cash at the Beginning of the Year | I54: =F54 -> 0
A55: CASH BALANCE AT THE END OF THE YEAR | I55: =SUM(I53:I54) -> 0
A57: Prepared by: | E57: Certified Correct:
F58: =F55-F57 -> 0
A59: JESSA S. CABIYAAN | E59: JUDY G. PARADO, CPA | M59: tb
A60: Admin. Aide III | E60: Municipal Accountant

Sheet Balance Sheet
A1: Republic of the Philippines
A2: Province o0f Leyte
A3: Municipality of Jaro
A5: BALANCE SHEET
A6: General Fund
A7: As of December 31, 2015
A8: (With Comparative Figures for CY 2014)
G11: 2015 | I11: 2014
A12: ASSETS
A13: CURRENT ASSETS
A14: CASH
A15: Cash on Hand
B16: Cash in Vault | G16: ='Schedule Balance Sheet'!E13 -> 3359712.5 | I16: 587123.05
B17: Cash-Disbursing Officers
B18: Petty Cash Fund | G18: ='Schedule Balance Sheet'!E17 -> 43642.37 | I18: 43642.37
B19: Payroll Fund | G19: ='Schedule Balance Sheet'!E19 -> #REF! | I19: 0.01
A20: Cash in Banks-Local Currency
B21: Cash in Bank-Local Currency, Current Account | G21: ='Schedule Balance Sheet'!E33 -> 71163818 | I21: 29001618
B22: Cash in Bank-Local Currency, Savings Account
B23: Cash in Bank-Local Currency, Time Deposits
A24: Cash in Banks-Foreign Currency
B25: Cash in Bank-Foreign Currency, Current Account
B26: Cash in Bank-Foreign Currency, Savings Account
B27: Cash in Bank-Foreign Currency, Time Deposits
A28: Total Cash | G28: =SUM(G15:G27) -> #REF! | I28: =SUM(I15:I27) -> 29632383
A29: RECEIVABLES
A30: Receivable Account
B31: Accounts Receivable
B32: Notes Receivables
B33: Due from Officers and Employees | G33: 0 | I33: 643610.24
B34: Loans Receivables-GOCCs
B35: Loans Receivables-Others
B36: Loans Receivables-LGUs
B37: Real Propery Tax Receivable | G37: ='Schedule Balance Sheet'!E38 -> 24158078 | I37: 24118803
B38: Special Education Tax Receivable
B39: Interests Receivable
A40: Inter-agency Receivables
B41: Due from NGAs | G41: ='Schedule Balance Sheet'!E39 -> #REF! | I41: 33742.13
B42: Due from GOCCs | G42: ='Schedule Balance Sheet'!E40 -> #REF! | I42: 3050.23
B43: Due from LGUs | G43: ='Schedule Balance Sheet'!E41 -> #REF! | I43: 85141.1
B44: Due from NGOs/Pos
A45: Intra-agency Receivables
B46: Due from Other Funds | G46: ='Schedule Balance Sheet'!E42 -> 626192.34 | I46: 616844.95
A47: Other Receivables
B48: Receivables-Disallowances/Charges | G48: ='Schedule Balance Sheet'!E43 -> 23333.02 | I48: 14953.02
B49: Advances to Officers and Employees | G49: ='Schedule Balance Sheet'!E44 -> 4540207.9 | I49: 6087160.5
B50: Other Receivables | G50: ='Schedule Balance Sheet'!E45 -> #REF! | I50: 250.84
A51: Total Receivables | G51: =SUM(G30:G50) -> #REF! | I51: =SUM(I30:I50) -> 31603556
A52: INVENTORIES
A53: Materials
B54: Raw Materials Inventory
B55: Work-in Process Inventoy
B56: Finished Goods Inventory
B57: Merchandise Inventory
A58: Supplies
B59: Office Supplies Inventory | G59: ='Schedule Balance Sheet'!E49 -> 17842.5
B60: Accountable Forms Inventory
B61: Animal/Zoological Supplies Inventory
B62: Food Supplies Inventory
B63: Drugs and Medicines Inventory
B64: Medical, Dental and Laboratory Supplies Inventory
B65: Gasoline, Oil and Lubricants Inventory
B66: Agricultural Supplies Inventory
B67: Textbooks and Instructional Materials Inventory
B68: Military and Police Supplies Inventory
B69: Other Supplies Inventoy | G69: ='Schedule Balance Sheet'!E50 -> 145607.6
B70: Confiscated/Abandoned/Seized Goods Inventory
B71: Spare Parts Inventory
B72: Construction Materials Inventory | G72: ='Schedule Balance Sheet'!E51 -> 180
A73: Agricultural, Fishery and Forestry Products
B74: Livestock Inventory | G74: ='Schedule Balance Sheet'!E52 -> #REF! | I74: 24000
B75: Crops and Fruits Inventory
B76: Other Agricultural, Fishery and Forestry Products Inventory
A77: Total Inventories | G77: =SUM(G53:G76) -> #REF! | I77: =SUM(I53:I76) -> 24000
A78: PREPAYMENTS
A79: Prepaid Rent
A80: Prepaid Insurance | G80: ='Schedule Balance Sheet'!E56 -> 12893.88 | I80: 39897.98
A81: Prepaid Interest
A82: Deposit on Letters of Credit
A83: Advances to Contractors | G83: ='Schedule Balance Sheet'!E57 -> 323539.58
A84: Deferred Charges
A85: Other Prepaid Expenses
A86: Total Prepayments | G86: =SUM(G79:G85) -> 336433.46 | I86: =SUM(I79:I85) -> 39897.98
A87: OTHER CURRENT ASSETS
A88: Guaranty Deposits
A89: Other Current Assets
A90: Total Other Current Assets
A91: TOTAL CURRENT ASSETS | G91: =G28+G51+G77+G86+G90 -> #REF! | I91: =I28+I51+I77+I86+I90 -> 61299837
A92: INVESTMENTS
A93: Investments in Treasury Bills
A94: Investments in Stocks
A95: Investments in Bonds
A96: Other Investments and Marketable Securities
A97: Sinking Fund
A98: TOTAL INVESTMENTS
A99: PROPERTY, PLANT AND EQUIPMENT (Net of Depreciation)
A100: LAND AND LAND IMPROVEMENTS
A101: Land | G101: ='Schedule Balance Sheet'!E61 -> 6961640 | I101: 8710510
A102: Land Improvements | G102: ='Schedule Balance Sheet'!E62 -> #REF! | I102: 14263749
A103: Electrification, Power and Energy Strucutres | G103: ='Schedule Balance Sheet'!E65 -> #REF! | I103: 960.39
...

Sheet Subsidiary Schedule
A1: Republic of the Philippines
A2: Province of Leyte
A3: MUNICIPALITY OF JARO
A5: SUBSIDIARY SCHEDULE
A6: As of December 31, 2019
A7: G E N E R A L F U N D
A9: ACCOUNT CODE | D9: PARTICULARS | E9: AMOUNT | I9: 1 | J9: 1 | K9: 2 | L9: 3 | M9: 4 | N9: 5
A10: Schedule | B10: 1 - | C10: 1-01-01-010 | D10: Cash Local Treasury | E10: ='[5]Cash Local Treasury'!$H$440 -> 397449.11 | H10: DEBIT | I10: =SUM(E10,E14,E24,E26,E28,E30,E32,E34,E48,E50,E52,E128,E130,E132,E134,E136,E138,E140,E142,E144,E146,E148,E150,E152,E156,E158,E160,E162,E164,E166) -> 2.09604e+08 | J10: =SUM(E168,E170,E172,E174,E176,E178,E182,E184,E186,E188,E190,E192,E194,E196,E198,E200) -> 87798437 | L10: =E314 -> 16512.58 | M10: =E322 -> 87927.35 | N10: =SUM(E378:E500) -> 1.0410666e+08 | O10: =SUM(I10:N10) -> 4.0161354e+08
A11: Schedule | B11: 2 - | D11: Petty Cash | H11: CREDIT | I11: =SUM(E202,E204,E206,E208,E210,E212,E214,E216,E218,E220,E222,E226) -> 10835277 | K11: =SUM(E233,E235,E243,E258,E264,E269,E279,E287,E292,E301,E303,E305,E307) -> 38648355 | L11: =E312 -> 2.0633173e+08 | M11: =SUM(E316,E318,E320,E324,E326,E328,E330,E332,E334,E336,E338,E340,E342,E344,E346,E348,E350,E352,E354,E356,E358,E360,E362,E364,E366,E368,E370,E372,E374,E376) -> 1.381462e+08 | O11: =SUM(I11:N11) -> 3.9396156e+08
C12: 1-01-01-020 - 1 | D12: GENERAL FUND | E12: ='[5]Petty Cash-1'!$G$47 -> 21642.37 | H12: DIFFERENCE | N12: TB TOTAL | O12: =[6]December!$F$186 -> 3.6359049e+08
C13: 1-01-01-020 - 2 | D13: AICS | E13: ='[5]Petty Cash-2'!$G$46 -> 22000 | O13: =O12-O11 -> -30371071
C14: TOTAL | E14: =SUM(E12:E13) -> 43642.37
A16: Schedule | B16: 3 - | C16: 1-01-02-010 | D16: Cash in Bank - Local Currency, Current Account
C17: 1-01-02-010 - 1A | D17: IRA | E17: ='[5]CIB- Mun. IRA'!$H$1826 -> 49207976
C18: 1-01-02-010 - 1B | D18: RIMMP | E18: ='[5]CIB-RIMMP'!$G$45 -> 14328.66
C19: 1-01-02-010 - 1C | D19: LGU EQUITY - PNP | E19: ='[5]CIB- LGU Equity'!$G$45 -> 33326.04
C20: 1-01-02-010 - 2 | D20: LBP 20% | E20: ='[5]CIB-20% (-2)'!$G$72 -> 1005024.4
C21: 1-01-02-010 - 3 | D21: PPSB (5%) | E21: =SUM('[5]CIB-3-70%'!$H$88,'[5]CIB-3-30% QUICK RESPONSE FUND'!$G$46) -> 0
C22: 1-01-02-010 - 4 | D22: DBP (20%) | E22: ='[5]CIB (-4) - DBP (20%)'!$G$84 -> 15454977
C23: 1-01-02-010 - 5 | D23: DBP (5%) | E23: ='[5]CIB (-5) - DBP (5%)'!$G$75 -> 23209543
C24: TOTAL | E24: =SUM(E17:E23) -> 88925175
A26: Schedule | B26: 4 - | C26: 1-02-05-990 | D26: Other Investments | E26: ='[7]Other Investments'!$G$45 -> 72000
A28: Schedule | B28: 5 - | C28: 1-03-01-020 | D28: Real Property Tax Receivable | E28: ='[8]RPT Receivable'!$G$141 -> 17255192
A30: Schedule | B30: 6 - | C30: 1-03-03-010 | D30: Due from National Government Agencies | E30: ='[8]Due from Nat''l Gov''t Agencies'!$G$45 -> 33742.13
A32: Schedule | B32: 7 - | C32: 1-03-03-020 | D32: Due from GOCCs | E32: ='[8]Due from GOCCs'!$G$45 -> 45818.23
A34: Schedule | B34: 8 - | C34: 1-03-03-030 | D34: Due from LGUs | E34: ='[8]Due from LGUs'!$G$45 -> 85141.1
A36: Schedule | B36: 9 - | C36: 1-03-04-050 | D36: Due from Other Funds
C37: 1-03-04-050 - 1 | E37: ='[8]Due from Other Funds - Unknown'!$G$12 -> 616844.94
C38: 1-03-04-050 - 2 | D38: DBP | E38: ='[8]Due from Other Funds-DBP'!$G$48 -> 3204899.5
C39: 1-03-04-050 - 3 | D39: SEF | E39: ='[8]Due from Other Funds-SEF'!$G$68 -> 7394.72
C40: 1-03-04-050 - 4 | D40: TRUST FUND | E40: ='[8]Due from Other Funds-TF'!$G$73 -> -115307.86
C41: 1-03-04-050 - 5 | D41: SALINTUBIG | E41: ='[8]Due from Other Funds-SALINTUBIG'!$G$62 -> 9985053.5
C42: 1-03-04-050 - 6 | D42: PCF | E42: ='[8]Due from Other Funds-PCF'!$G$45 -> 127
C43: 1-03-04-050 - 7 | D43: GPBP | E43: ='[8]Due from Other Funds - GPBP'!$G$52 -> 0
C44: 1-03-04-050 - 8 | D44: JARO SPORTS COMPLEX (JSC) | E44: ='[8]Due from Other Funds - JSC'!$G$50 -> 4164799.1
C45: 1-03-04-050 - 9 | D45: KFW | E45: ='[8]Due from Other Funds - KWF'!$G$55 -> 3166644.7
C46: 1-03-04-050 - 10 | D46: RAY 2 | E46: ='[8]Due from Other Funds - RAY 2'!$G$45 -> 0
C47: 1-03-04-050 - 11 | D47: RAY 3 | E47: ='[8]Due from Other Funds - RAY 3'!$G$46 -> 5625
C48: TOTAL | E48: =SUM(E37:E47) -> 21036081
A50: Schedule | B50: 10 - | C50: 1-03-05-010 | D50: Advances for Operating Expenses | E50: =[9]December!$C$20 -> 709400
A52: Schedule | B52: 11 - | C52: 1-03-05-020 | D52: Advances for Payroll | E52: =[9]December!$C$21 -> 1000.81
A54: Schedule | B54: 12 - | C54: 1-03-05-040 | D54: Advances for Officers and Employees
C55: 1-03-05-040 - 1 | D55: Alex O. Aborita | E55: ='[10]4th Quarter'!$J$19 -> 8910
C56: 1-03-05-040 - 2 | D56: Alexandra O. Aborita | E56: ='[10]4th Quarter'!$J$21 -> 9020
C57: 1-03-05-040 - 3 | D57: Alfredo Capoquian | E57: ='[10]4th Quarter'!$J$24 -> 7100
C58: 1-03-05-040 - 4 | D58: Angel Romeo Caones | E58: ='[10]4th Quarter'!$J$26 -> 6600
C59: 1-03-05-040 - 5 | D59: Annabelle V. De Asis | E59: ='[10]4th Quarter'!$J$31 -> 25840
C60: 1-03-05-040 - 6 | D60: Antonio Batucan | E60: ='[10]4th Quarter'!$J$36 -> 13799
C61: 1-03-05-040 - 7 | D61: Arvin D. Aborita | E61: ='[10]4th Quarter'!$I$38 -> 15720
C62: 1-03-05-040 - 8 | D62: Aquilino Colibao | E62: ='[10]4th Quarter'!$F$40 -> 5800
C63: 1-03-05-040 - 9 | D63: Beau Francis Lagado | E63: ='[10]4th Quarter'!$J$56 -> 160500
C64: 1-03-05-040 - 10 | D64: Benjamin Gariando Sr. | E64: ='[10]4th Quarter'!$J$65 -> 20912
C65: 1-03-05-040 - 11 | D65: Clarissa Matoza | E65: ='[10]4th Quarter'!$J$74 -> 13316
C66: 1-03-05-040 - 12 | D66: Elma C. Cañega | E66: ='[10]4th Quarter'!$G$78 -> 1382
C67: 1-03-05-040 - 13 | D67: Eva A. Royo | E67: ='[10]4th Quarter'!$H$80 -> 2053.58
C68: 1-03-05-040 - 14 | D68: E. Adlawan | E68: ='[10]4th Quarter'!$J$82 -> 200
C69: 1-03-05-040 - 15 | D69: Elias C. Susaya, Jr. | E69: ='[10]4th Quarter'!$J$84 -> 9800
C70: 1-03-05-040 - 16 | D70: Edgar Artoza | E70: ='[10]4th Quarter'!$J$87 -> 5570
C71: 1-03-05-040 - 17 | D71: Edgar Raagas | E71: ='[10]4th Quarter'!$E$93 -> 39397.38
C72: 1-03-05-040 - 18 | D72: Elena A. Emnas | E72: ='[10]4th Quarter'!$F$95 -> 17470
C73: 1-03-05-040 - 19 | D73: Estela I. Creer | E73: ='[10]4th Quarter'!$J$97 -> 5900
C74: 1-03-05-040 - 20 | D74: Felipe A. Castillano | E74: ='[10]4th Quarter'!$J$109 -> 23740
C75: 1-03-05-040 - 21 | D75: Floro Katangkatang | E75: ='[10]4th Quarter'!$J$120 -> 1109933.5
C76: 1-03-05-040 - 22 | D76: Frankie A. Tezon | E76: ='[10]4th Quarter'!$J$124 -> 4800
C77: 1-03-05-040 - 23 | D77: Gloria C. Villas | E77: ='[10]4th Quarter'!$H$128 -> 2174.08
C78: 1-03-05-040 - 24 | D78: Hassan Cabelin | E78: ='[10]4th Quarter'!$J$144 -> 268679
C79: 1-03-05-040 - 25 | D79: Jaime C. Lagado | E79: ='[10]4th Quarter'!$J$164 -> 164675.6
C80: 1-03-05-040 - 26 | D80: Jay G. Saliente | E80: ='[10]4th Quarter'!$J$172 -> 133100
C81: 1-03-05-040 - 27 | D81: Jay G. Saliente c/o INFRES | E81: ='[10]4th Quarter'!$J$174 -> 10000
C82: 1-03-05-040 - 28 | D82: Jessica Josol | E82: ='[10]4th Quarter'!$J$176 -> 520
C83: 1-03-05-040 - 29 | D83: Jesucita Guillera | E83: ='[10]4th Quarter'!$J$178 -> 430
C84: 1-03-05-040 - 30 | D84: Jofrey Gonzaga | E84: ='[10]4th Quarter'!$J$182 -> 10760
C85: 1-03-05-040 - 31 | D85: Johannes Dorado | E85: ='[10]4th Quarter'!$J$184 -> 5900
C86: 1-03-05-040 - 32 | D86: Jovino G. Niemes | E86: ='[10]4th Quarter'!$J$186 -> 610
C87: 1-03-05-040 - 33 | D87: Juancho C. Bonayon | E87: ='[10]4th Quarter'!$J$229 -> 389337.08
C88: 1-03-05-040 - 34 | D88: Julius B. Cativo | E88: ='[10]4th Quarter'!$F$231 -> 15490
C89: 1-03-05-040 - 35 | D89: Joebel Garciola | E89: ='[10]4th Quarter'!$H$233 -> 995.84
C90: 1-03-05-040 - 36 | D90: Leonil Jun Arañez | E90: ='[10]4th Quarter'!$F$235 -> 8700
C91: 1-03-05-040 - 37 | D91: Lorenzo M. Lariosa | E91: ='[10]4th Quarter'!$J$242 -> 3826
C92: 1-03-05-040 - 38 | D92: Ma. Lourdes F. Opinion | E92: ='[10]4th Quarter'!$J$255 -> 8222
C93: 1-03-05-040 - 39 | D93: Maria Wilma T. Lizarondo | E93: ='[10]4th Quarter'!$G$257 -> 21000
C94: 1-03-05-040 - 40 | D94: Melchor Winston A. Edusma | E94: ='[10]4th Quarter'!$J$259 -> 9000
C95: 1-03-05-040 - 41 | D95: Mig Joy T. Boleche | E95: ='[10]4th Quarter'!$J$261 -> 22414
C96: 1-03-05-040 - 42 | D96: P. Espinosa | E96: ='[10]4th Quarter'!$J$269 -> 300
C97: 1-03-05-040 - 43 | D97: Pablito H. Quiñones | E97: ='[10]4th Quarter'!$J$271 -> 10000
C98: 1-03-05-040 - 44 | D98: Patria H. Gariando | E98: ='[10]4th Quarter'!$J$273 -> 470
C99: 1-03-05-040 - 45 | D99: Redonia K. Tamayo | E99: ='[10]4th Quarter'!$I$277 -> 1380
C100: 1-03-05-040 - 46 | D100: Renerio Horca | E100: ='[10]4th Quarter'!$J$279 -> 6940
C101: 1-03-05-040 - 47 | D101: Rey P. Aure | E101: ='[10]4th Quarter'!$F$281 -> 30064
C102: 1-03-05-040 - 48 | D102: Rolando Nievera | E102: ='[10]4th Quarter'!$J$283 -> 5100
C103: 1-03-05-040 - 49 | D103: Romeo S. Trota, Jr. | E103: ='[10]4th Quarter'!$J$291 -> 2535
C104: 1-03-05-040 - 50 | D104: Solomon U. Aujero | E104: ='[10]4th Quarter'!$J$297 -> 8300
C105: 1-03-05-040 - 51 | D105: Sonia A. Yunting | E105: ='[10]4th Quarter'!$J$302 -> 35575.6
C106: 1-03-05-040 - 52 | D106: Teofila L. Go | E106: ='[10]4th Quarter'!$G$304 -> 1633.5
C107: 1-03-05-040 - 53 | D107: Teofilo C. Cabello | E107: ='[10]4th Quarter'!$F$306 -> 421
C108: 1-03-05-040 - 54 | D108: T. Gelig | E108: ='[10]4th Quarter'!$J$308 -> 200
C109: 1-03-05-040 - 55 | D109: Yvette M. Dizon | E109: ='[10]4th Quarter'!$J$318 -> 85843.4
C110: 1-03-05-040 - 56 | D110: Zoilo S. Trota II | E110: ='[10]4th Quarter'!$J$328 -> 18766
C111: 1-03-05-040 - 57 | D111: Nestor C. Tamayo (TEV) | E111: ='[10]4th Quarter'!$J$330 -> 25000
C112: 1-03-05-040 - 58 | D112: Nestor C. Tamayo (c/o Others) | E112: ='[10]4th Quarter'!$J$335 -> 62879
...
